awsio/__init__.py
awsio/auth.py
awsio/config.py
awsio/io.py
awsio/parallelism.py
awsio/path.py
awsio/versioned.py
awsio-0.2.0.dist-info/licenses/LICENSE
awsio-0.2.0.dist-info/METADATA
awsio-0.2.0.dist-info/WHEEL
awsio-0.2.0.dist-info/top_level.txt
awsio-0.2.0.dist-info/RECORD
