Metadata-Version: 2.4
Name: awsio
Version: 0.2.0
Summary: Utilities library for read/write operations and general data cleaning routines
Author-email: João Pedro Alves <jotapedro1997@gmail.com>
Project-URL: Homepage, https://github.com/jotap123/awsio/tree/develop
Project-URL: Issues, https://github.com/jotap123/awsio/issues
Project-URL: Linkedin_JP, https://www.linkedin.com/in/jp111/
Classifier: Programming Language :: Python :: 3.10
Classifier: Programming Language :: Python :: 3.11
Classifier: Programming Language :: Python :: 3.12
Classifier: Programming Language :: Python :: 3.13
Classifier: Operating System :: OS Independent
Classifier: Development Status :: 4 - Beta
Requires-Python: >=3.10
License-File: LICENSE
Requires-Dist: boto3
Requires-Dist: numpy
Requires-Dist: pandas
Requires-Dist: joblib
Requires-Dist: pyarrow
Requires-Dist: openpyxl
Requires-Dist: python-dotenv
Requires-Dist: awswrangler
Dynamic: license-file
